transportapi_python/__init__.py
transportapi_python/transportapi.py
transportapi_python-0.0.1.dist-info/LICENSE
transportapi_python-0.0.1.dist-info/METADATA
transportapi_python-0.0.1.dist-info/WHEEL
transportapi_python-0.0.1.dist-info/top_level.txt
transportapi_python-0.0.1.dist-info/RECORD
