Metadata-Version: 2.1
Name: transportapi-python
Version: 0.0.1
Summary: Unofficial Python 3.7 API wrapper for the TransportAPI.
Home-page: https://github.com/Dextroz/transportapi-python
Author: Dextroz
License: UNKNOWN
Keywords: Wrapper API Transport TransportAPI Library Car Bus Bike Public Bicycle Train
Platform: UNKNOWN
Classifier: License :: OSI Approved :: MIT License
Classifier: Programming Language :: Python :: 3
Classifier: Programming Language :: Python :: 3.7
